gpkit_models-0.1.0.dist-info/licenses/LICENSE
gpkitmodels/__init__.py
gpkitmodels/GP/__init__.py
gpkitmodels/GP/aircraft/__init__.py
gpkitmodels/GP/aircraft/engine/__init__.py
gpkitmodels/GP/aircraft/engine/df70.py
gpkitmodels/GP/aircraft/engine/gas_engine.py
gpkitmodels/GP/aircraft/engine/powerBSFCfit.csv
gpkitmodels/GP/aircraft/engine/power_lawfit.csv
gpkitmodels/GP/aircraft/engine/DF70/DF35_maxPvh.csv
gpkitmodels/GP/aircraft/engine/DF70/Dataset_BSFC_kgKwh.csv
gpkitmodels/GP/aircraft/engine/DF70/Dataset_Power_Kw.csv
gpkitmodels/GP/aircraft/engine/DF70/Dataset_Torque_Nm.csv
gpkitmodels/GP/aircraft/engine/DF70/fitDF70.py
gpkitmodels/GP/aircraft/engine/DF70/genericbsfcpower.csv
gpkitmodels/GP/aircraft/fuselage/__init__.py
gpkitmodels/GP/aircraft/fuselage/cylindrical_fuselage.py
gpkitmodels/GP/aircraft/fuselage/elliptical_fuselage.py
gpkitmodels/GP/aircraft/fuselage/fuel_tank.py
gpkitmodels/GP/aircraft/fuselage/fuselage_skin.py
gpkitmodels/GP/aircraft/fuselage/test_fuselage.py
gpkitmodels/GP/aircraft/fuselage/fuselage_profile_drag/fusedrag.csv
gpkitmodels/GP/aircraft/fuselage/fuselage_profile_drag/fusedragfit.py
gpkitmodels/GP/aircraft/mission/__init__.py
gpkitmodels/GP/aircraft/mission/breguet_endurance.py
gpkitmodels/GP/aircraft/motor/__init__.py
gpkitmodels/GP/aircraft/motor/motor.py
gpkitmodels/GP/aircraft/motor/motor_test.py
gpkitmodels/GP/aircraft/prop/__init__.py
gpkitmodels/GP/aircraft/prop/arccos_fit.py
gpkitmodels/GP/aircraft/prop/prop_test.py
gpkitmodels/GP/aircraft/prop/propeller.py
gpkitmodels/GP/aircraft/tail/__init__.py
gpkitmodels/GP/aircraft/tail/empennage.py
gpkitmodels/GP/aircraft/tail/horizontal_tail.py
gpkitmodels/GP/aircraft/tail/tail_aero.py
gpkitmodels/GP/aircraft/tail/tail_boom.py
gpkitmodels/GP/aircraft/tail/tail_dragfit.csv
gpkitmodels/GP/aircraft/tail/tail_tests.py
gpkitmodels/GP/aircraft/tail/tube_spar.py
gpkitmodels/GP/aircraft/tail/vertical_tail.py
gpkitmodels/GP/aircraft/tail/tailpolars/naca_cl0fits.py
gpkitmodels/GP/aircraft/wing/__init__.py
gpkit_models-0.1.0.dist-info/METADATA
gpkit_models-0.1.0.dist-info/WHEEL
gpkit_models-0.1.0.dist-info/top_level.txt
gpkit_models-0.1.0.dist-info/RECORD
