Metadata-Version: 2.4
Name: gpkit-models
Version: 0.1.0
Summary: Library of exponential cone compatible sizing models
Author-email: Warren Hoburg <whoburg@alum.mit.edu>
License: MIT License
Project-URL: Homepage, https://www.github.com/beautifulmachines/gpkit-models
Requires-Python: >=3.8
License-File: LICENSE
Requires-Dist: adce>=1.3.3.2
Requires-Dist: gpkit-core>=0.1.0
Requires-Dist: pandas>=2.0.0
Provides-Extra: lint
Requires-Dist: isort>=5.12.0; extra == "lint"
Requires-Dist: black>=24.1.0; extra == "lint"
Requires-Dist: pylint>=3.0.0; extra == "lint"
Requires-Dist: flake8>=7.0.0; extra == "lint"
Provides-Extra: test
Requires-Dist: pytest>=7.0.0; extra == "test"
Dynamic: license-file
